LICENSE
MANIFEST.in
README.md
setup.py
tests/test_mask_creation.py
tests/test_pytorch_prop_function.py
tests/test_simulate.py
waveprop/__init__.py
waveprop/color.py
waveprop/condition.py
waveprop/dataset_util.py
waveprop/devices.py
waveprop/fraunhofer.py
waveprop/fresnel.py
waveprop/holography.py
waveprop/io.py
waveprop/noise.py
waveprop/pytorch_util.py
waveprop/rs.py
waveprop/simulation.py
waveprop/slm.py
waveprop/spherical.py
waveprop/util.py
waveprop.egg-info/PKG-INFO
waveprop.egg-info/SOURCES.txt
waveprop.egg-info/dependency_links.txt
waveprop.egg-info/requires.txt
waveprop.egg-info/top_level.txt
waveprop/lookup/cie-cmf.txt
waveprop/lookup/illuminant_d65.txt