Metadata-Version: 2.2
Name: waveprop
Version: 0.0.12
Summary: Functions and scripts to simulate free-space optical wave propagation.
Home-page: https://github.com/ebezzam/waveprop
Author: Eric Bezzam
Author-email: ebezzam@gmail.com
Classifier: Programming Language :: Python :: 3
Classifier: Operating System :: OS Independent
Requires-Python: >=3.9
License-File: LICENSE
Requires-Dist: torch>=1.12.1
Requires-Dist: torchvision>=0.13.1
Requires-Dist: opencv-python
Requires-Dist: numpy
Requires-Dist: scipy
Requires-Dist: matplotlib
Requires-Dist: pyffs
Requires-Dist: progressbar
Dynamic: author
Dynamic: author-email
Dynamic: classifier
Dynamic: description
Dynamic: description-content-type
Dynamic: home-page
Dynamic: requires-dist
Dynamic: requires-python
Dynamic: summary
